bulk_mv/__init__.py
bulk_mv/__main__.py
bulk_mv/bmv.lark
bulk_mv/bmv_generator.py
bulk_mv/bmv_parser.py
bulk_mv/cli.py
bulk_mv/file_tree.py
bulk_mv/file_tree_builder.py
bulk_mv/helpers.py
bulk_mv/operations.py
bulk_mv/tests/test_bmv_generator.py
bulk_mv/tests/test_bmv_parser.py
bulk_mv/tests/test_file_tree.py
bulk_mv/tests/test_file_tree_builder.py
bulk_mv/tests/test_helpers.py
bulk_mv/tests/test_operations.py
bulk_mv/tests/dummy_bmv_files/sample1.bmv
bulk_mv/tests/dummy_bmv_files/sample3.bmv
bulk_mv/tests/dummy_directories/sample1/index.html
bulk_mv/tests/dummy_directories/sample1/admin/index.html
bulk_mv/tests/dummy_directories/sample1/admin/nichoal.html
bulk_mv/tests/dummy_directories/sample1/users/angel.html
bulk_mv/tests/dummy_directories/sample1/users/index.html
bulk_mv/tests/dummy_directories/sample1/users/josh.html
bulk_mv/tests/dummy_directories/sample1/users/blocked/blocked_user_1.html
bulk_mv/tests/dummy_directories/sample2/a.txt
bulk_mv/tests/dummy_directories/sample2/b.txt
bulk_mv/tests/dummy_directories/sample2/c.txt
bulk_mv/tests/dummy_directories/sample2/readme.md
bulk_mv/tests/dummy_directories/sample2/data/report.csv
bulk_mv/tests/dummy_directories/sample2/web/index.html
bulk_mv/tests/dummy_directories/sample2/web/main.css
bulk_mv/tests/dummy_directories/sample2/web/main.js
bulk_mv/tests/dummy_directories/sample3/delete/no_more.html
bulk_mv/tests/dummy_directories/sample3/markdown/1.md
bulk_mv/tests/dummy_directories/sample3/markdown/2.md
bulk_mv/tests/dummy_directories/sample3/photos/test.jpg
bulk_mv/tests/dummy_directories/sample3/text/1.txt
bulk_mv/tests/dummy_directories/sample3/text/2.txt
bulk_mv-0.1.5.dist-info/LICENSE
bulk_mv-0.1.5.dist-info/METADATA
bulk_mv-0.1.5.dist-info/WHEEL
bulk_mv-0.1.5.dist-info/entry_points.txt
bulk_mv-0.1.5.dist-info/top_level.txt
bulk_mv-0.1.5.dist-info/RECORD
